runome-0.1.0.dist-info/METADATA
runome-0.1.0.dist-info/WHEEL
runome/__init__.py
runome/analyzer.py
runome/charfilter.py
runome/runome.abi3.so
runome/runome.pyi
runome/sysdic/char_defs.bin
runome/sysdic/connections.bin
runome/sysdic/dic.fst
runome/sysdic/entries.bin
runome/sysdic/morpheme_index.bin
runome/sysdic/unknowns.bin
runome/tokenfilter.py
runome/tokenizer.py
runome-0.1.0.dist-info/RECORD
