Metadata-Version: 2.4
Name: runome
Version: 0.1.0
Summary: Japanese morphological analyzer compatible with Janome
Requires-Python: >=3.8
